AUTHORS.rst
CONTRIBUTING.rst
HISTORY.rst
LICENSE
MANIFEST.in
README.rst
setup.cfg
setup.py
connector_events.egg-info/PKG-INFO
connector_events.egg-info/SOURCES.txt
connector_events.egg-info/dependency_links.txt
connector_events.egg-info/not-zip-safe
connector_events.egg-info/requires.txt
connector_events.egg-info/top_level.txt
events/__init__.py
events/admin.py
events/feeds.py
events/forms.py
events/models.py
events/urls.py
events/views.py
events/migrations/0001_initial.py
events/migrations/0002_auto__add_field_event_notes.py
events/migrations/0003_auto__add_field_event_description_markdown.py
events/migrations/0004_auto__chg_field_event_description.py
events/migrations/0005_auto__add_field_event_slug.py
events/migrations/0006_auto__add_field_event_uid.py
events/migrations/__init__.py
events/templates/events/event_detail.html
events/templates/events/event_list.html
events/templatetags/__init__.py
events/templatetags/events_tags.py