Metadata-Version: 1.1
Name: connector-events
Version: 0.1.0
Summary: Events app primarily for the 'connector' events & community aggregator
Home-page: https://github.com/rva-data/connector-events
Author: Ben Lopatin
Author-email: ben@wellfire.co
License: BSD
Keywords: connector-events
Platform: UNKNOWN
Classifier: Development Status :: 2 - Pre-Alpha
Classifier: Framework :: Django
Classifier: Intended Audience :: Developers
Classifier: License :: OSI Approved :: BSD License
Classifier: Natural Language :: English
Classifier: Programming Language :: Python :: 2
Classifier: Programming Language :: Python :: 2.6
Classifier: Programming Language :: Python :: 2.7
Classifier: Programming Language :: Python :: 3
Classifier: Programming Language :: Python :: 3.3
